Metadata-Version: 2.1
Name: muj-package
Version: 1.0.0
Summary: Testing package cz14
Home-page: UNKNOWN
Author: ja
Author-email: john.doe@gmail.com
License: UNKNOWN
Platform: UNKNOWN
